{
  "$schema": "https://raw.githubusercontent.com/grafana/grafana/master/docs/sources/developers/plugins/plugin.schema.json",
  "type": "datasource",
  "name": "FlightSQL",
  "id": "influxdata-flightsql-datasource",
  "metrics": true,
  "backend": true,
  "alerting": true,
  "executable": "gpx_flightsql_datasource",
  "info": {
    "description": "Query databases that support Flight SQL transport.",
    "author": {
      "name": "InfluxData",
      "url": "https://influxdata.com"
    },
    "keywords": ["datasource", "apache", "arrow", "flight", "flightsql"],
    "logos": {
      "small": "img/arrow-logo.png",
      "large": "img/arrow-logo.png"
    },
    "links": [
      {
        "name": "Website",
        "url": "https://github.com/influxdata/grafana-flightsql-datasource"
      }
    ],
    "screenshots": [
      {
        "name": "Config Data Source",
        "path": "img/datasource-configuration.png"
      },
      {
        "name": "Builder View Query",
        "path": "img/builder-view-query.png"
      },
      {
        "name": "Raw Editor Query",
        "path": "img/raw-editor-query.png"
      }
    ],
    "version": "%VERSION%",
    "updated": "%TODAY%"
  },
  "dependencies": {
    "grafanaDependency": "^9.2.5",
    "plugins": []
  }
}
